{"is_source_file": true, "format": "JavaScript (React JSX)", "description": "A React component named RecipeCard that renders a card UI for a recipe, displaying an image, title, category, and preparation time, with navigation linking to a detailed recipe page.", "external_files": ["react", "react-router-dom"], "external_methods": ["Link from react-router-dom"], "published": ["RecipeCard"], "classes": [], "methods": [{"name": "RecipeCard({ recipe })", "description": "A functional React component that renders a recipe card with image, title, category, and time, linking to the detailed recipe page.", "scope": "", "scopeKind": ""}], "calls": ["React", "Link"], "search-terms": ["RecipeCard", "React component", "recipe display", "jsx", "react-router-dom Link"], "state": 2, "file_id": 20, "knowledge_revision": 44, "git_revision": "", "ctags": [{"_type": "tag", "name": "RecipeCard", "path": "/home/kavia/workspace/code-generation/recipe-explorer-31097-31106/recipes_frontend/src/components/RecipeCard.jsx", "pattern": "/^export default function RecipeCard({ recipe }) {$/", "language": "JavaScript", "kind": "function", "signature": "({ recipe })"}, {"_type": "tag", "name": "recipe", "path": "/home/kavia/workspace/code-generation/recipe-explorer-31097-31106/recipes_frontend/src/components/RecipeCard.jsx", "pattern": "/^          src={recipe.image}$/", "language": "JavaScript", "kind": "field", "scope": "RecipeCard.src", "scopeKind": "class"}, {"_type": "tag", "name": "title} recipe image", "path": "/home/kavia/workspace/code-generation/recipe-explorer-31097-31106/recipes_frontend/src/components/RecipeCard.jsx", "pattern": "/^          alt={`${recipe.title} recipe image`}$/", "language": "JavaScript", "kind": "field", "scope": "RecipeCard.alt.${recipe", "scopeKind": "class"}], "hash": "bdd0de3507a28bb360e0f7960fc9ac14", "format-version": 4, "code-base-name": "recipes_frontend", "filename": "recipes_frontend/src/components/RecipeCard.jsx", "fields": [{"name": "src={recipe.image}", "scope": "RecipeCard.src", "scopeKind": "class", "description": "unavailable"}, {"name": "alt={`${recipe.title} recipe image`}", "scope": "RecipeCard.alt.${recipe", "scopeKind": "class", "description": "unavailable"}], "revision_history": [{"44": ""}]}